COA/4BitALU/FourBitALU.v
module FourBitALU(
    input [3:0] A, B,
    input S1, S0, Cin,
    output [3:0] D,
    output Cout
);

    wire [3:0] Y;
    wire [4:0] result;

    assign Y = (S1 == 0 && S0 == 0) ? B :
                (S1 == 0 && S0 == 1) ? ~B :
                (S1 == 1)            ? 4'b0000 : 4'b0000;

    assign result = A + Y + Cin;

    assign D = result[3:0];
    assign Cout = result[4];

endmodule

COA/post minor/4BitALU/FourBitALU_tb.v
`timescale 1ns/1ps
module FourBitALU_tb;
    reg [3:0] A, B;
    reg S1, S0, Cin;
    wire [3:0] D;
    wire Cout;

    FourBitALU uut(.A(A), .B(B), .S1(S1), .S0(S0), .Cin(Cin), .D(D), .Cout(Cout));

    initial begin
        $dumpfile("FourBitALU.vcd");
        $dumpvars(0, FourBitALU_tb);
        $monitor("t=%0t A=%b B=%b S1=%b S0=%b Cin=%b -> D=%b Cout=%b", 
                  $time, A, B, S1, S0, Cin, D, Cout);

        A = 4'b0101; B = 4'b0011;
        //Cases: 
        S1=0; S0=0; Cin=0; #10; // Add
        S1=0; S0=0; Cin=1; #10; // Add with carry
        S1=0; S0=1; Cin=0; #10; // Subtract with borrow
        S1=0; S0=1; Cin=1; #10; // Subtract
        S1=1; S0=0; Cin=0; #10; // Transfer A
        S1=1; S0=0; Cin=1; #10; // Increment A
        S1=1; S0=1; Cin=0; #10; // Decrement A
        S1=1; S0=1; Cin=1; #10; // Transfer A again

        $finish;
    end
endmodule

COA/4BitALU/FourBitALU.vcd
$date
	Mon Oct 06 00:30:09 2025
$end
$version
	Icarus Verilog
$end
$timescale
	1ps
$end
$scope module FourBitALU_tb $end
$var wire 4 ! D [3:0] $end
$var wire 1 " Cout $end
$var reg 4 # A [3:0] $end
$var reg 4 $ B [3:0] $end
$var reg 1 % Cin $end
$var reg 1 & S0 $end
$var reg 1 ' S1 $end
$scope module uut $end
$var wire 4 ( A [3:0] $end
$var wire 4 ) B [3:0] $end
$var wire 1 % Cin $end
$var wire 1 & S0 $end
$var wire 1 ' S1 $end
$var wire 5 * result [4:0] $end
$var wire 4 + Y [3:0] $end
$var wire 4 , D [3:0] $end
$var wire 1 " Cout $end
$upscope $end
$upscope $end
$enddefinitions $end
#0
$dumpvars
b1000 ,
b11 +
b1000 *
b11 )
b101 (
0'
0&
0%
b11 $
b101 #
0"
b1000 !
$end
#10000
b1001 !
b1001 ,
b1001 *
1%
#20000
1"
b1100 +
b1 !
b1 ,
b10001 *
0%
1&
#30000
b10 !
b10 ,
b10010 *
1%
#40000
0"
b0 +
b101 !
b101 ,
b101 *
0%
0&
1'
#50000
b110 !
b110 ,
b110 *
1%
#60000
b101 !
b101 ,
b101 *
0%
1&
#70000
b110 !
b110 ,
b110 *
1%
