COA/bin/dec4x16.v
module dec2x4 (
    input [1:0] A,
    output [3:0] Y
);
    assign Y = 4'b0001 << A;    
endmodule

module dec4x16 (
    input [3:0] A,
    output [15:0] Y
);
    wire [3:0] deciding;
    wire [3:0] y3, y2, y1, y0;

    dec2x4 decideDEC(.A(A[3:2]), .Y(deciding));

    dec2x4 dec3(.A(A[1:0]), .Y(y3));
    dec2x4 dec2(.A(A[1:0]), .Y(y2));
    dec2x4 dec1(.A(A[1:0]), .Y(y1));
    dec2x4 dec0(.A(A[1:0]), .Y(y0));

    assign Y[15:12] = deciding[3] ? y3 : 4'b0000;
    assign Y[11:8] = deciding[2] ? y2 : 4'b0000;
    assign Y[7:4] = deciding[1] ? y1 : 4'b0000;
    assign Y[3:0] = deciding[0] ? y3 : 4'b0000;
    
endmodule

COA/bin/dec4x16_tb.v
`timescale 1ns/1ps
module dec4x16_tb;
    reg [3:0] A;
    wire [15:0] Y;

    dec4x16 uut(.A(A), .Y(Y));

    initial begin
        A = 0;
        end

    initial begin
        $dumpfile("dec4x16.vcd");
        $dumpvars(0, dec4x16_tb);
        $monitor("t = %0t A = %b -> Y = %b", $time, A, Y);
        for (integer i = 0; i < 16; i++) begin
            A = i;
            #5;
        end
        $finish;
    end
    
endmodule

COA/bin/dec4x16.vcd
$date
	Mon Sep 15 08:04:44 2025
$end
$version
	Icarus Verilog
$end
$timescale
	1ps
$end
$scope module dec4x16_tb $end
$var wire 16 ! Y [15:0] $end
$var reg 4 " A [3:0] $end
$scope module uut $end
$var wire 4 # A [3:0] $end
$var wire 4 $ y3 [3:0] $end
$var wire 4 % y2 [3:0] $end
$var wire 4 & y1 [3:0] $end
$var wire 4 ' y0 [3:0] $end
$var wire 4 ( deciding [3:0] $end
$var wire 16 ) Y [15:0] $end
$scope module dec0 $end
$var wire 2 * A [1:0] $end
$var wire 4 + Y [3:0] $end
$upscope $end
$scope module dec1 $end
$var wire 2 , A [1:0] $end
$var wire 4 - Y [3:0] $end
$upscope $end
$scope module dec2 $end
$var wire 2 . A [1:0] $end
$var wire 4 / Y [3:0] $end
$upscope $end
$scope module dec3 $end
$var wire 2 0 A [1:0] $end
$var wire 4 1 Y [3:0] $end
$upscope $end
$scope module decideDEC $end
$var wire 2 2 A [1:0] $end
$var wire 4 3 Y [3:0] $end
$upscope $end
$upscope $end
$scope begin $ivl_for_loop0 $end
$var integer 32 4 i [31:0] $end
$upscope $end
$upscope $end
$enddefinitions $end
#0
$dumpvars
b0 4
b1 3
b0 2
b1 1
b0 0
b1 /
b0 .
b1 -
b0 ,
b1 +
b0 *
b1 )
b1 (
b1 '
b1 &
b1 %
b1 $
b0 #
b0 "
b1 !
$end
#5000
b10 !
b10 )
b10 $
b10 1
b1 0
b10 %
b10 /
b1 .
b10 &
b10 -
b1 ,
b10 '
b10 +
b1 *
b1 "
b1 #
b1 4
#10000
b100 !
b100 )
b100 $
b100 1
b10 0
b100 %
b100 /
b10 .
b100 &
b100 -
b10 ,
b100 '
b100 +
b10 *
b10 "
b10 #
b10 4
#15000
b1000 !
b1000 )
b1000 $
b1000 1
b11 0
b1000 %
b1000 /
b11 .
b1000 &
b1000 -
b11 ,
b1000 '
b1000 +
b11 *
b11 "
b11 #
b11 4
#20000
b10000 !
b10000 )
b10 (
b10 3
b1 2
b1 $
b1 1
b0 0
b1 %
b1 /
b0 .
b1 &
b1 -
b0 ,
b1 '
b1 +
b0 *
b100 "
b100 #
b100 4
#25000
b100000 !
b100000 )
b10 $
b10 1
b1 0
b10 %
b10 /
b1 .
b10 &
b10 -
b1 ,
b10 '
b10 +
b1 *
b101 "
b101 #
b101 4
#30000
b1000000 !
b1000000 )
b100 $
b100 1
b10 0
b100 %
b100 /
b10 .
b100 &
b100 -
b10 ,
b100 '
b100 +
b10 *
b110 "
b110 #
b110 4
#35000
b10000000 !
b10000000 )
b1000 $
b1000 1
b11 0
b1000 %
b1000 /
b11 .
b1000 &
b1000 -
b11 ,
b1000 '
b1000 +
b11 *
b111 "
b111 #
b111 4
#40000
b100000000 !
b100000000 )
b100 (
b100 3
b10 2
b1 $
b1 1
b0 0
b1 %
b1 /
b0 .
b1 &
b1 -
b0 ,
b1 '
b1 +
b0 *
b1000 "
b1000 #
b1000 4
#45000
b1000000000 !
b1000000000 )
b10 $
b10 1
b1 0
b10 %
b10 /
b1 .
b10 &
b10 -
b1 ,
b10 '
b10 +
b1 *
b1001 "
b1001 #
b1001 4
#50000
b10000000000 !
b10000000000 )
b100 $
b100 1
b10 0
b100 %
b100 /
b10 .
b100 &
b100 -
b10 ,
b100 '
b100 +
b10 *
b1010 "
b1010 #
b1010 4
#55000
b100000000000 !
b100000000000 )
b1000 $
b1000 1
b11 0
b1000 %
b1000 /
b11 .
b1000 &
b1000 -
b11 ,
b1000 '
b1000 +
b11 *
b1011 "
b1011 #
b1011 4
#60000
b1000000000000 !
b1000000000000 )
b1000 (
b1000 3
b11 2
b1 $
b1 1
b0 0
b1 %
b1 /
b0 .
b1 &
b1 -
b0 ,
b1 '
b1 +
b0 *
b1100 "
b1100 #
b1100 4
#65000
b10000000000000 !
b10000000000000 )
b10 $
b10 1
b1 0
b10 %
b10 /
b1 .
b10 &
b10 -
b1 ,
b10 '
b10 +
b1 *
b1101 "
b1101 #
b1101 4
#70000
b100000000000000 !
b100000000000000 )
b100 $
b100 1
b10 0
b100 %
b100 /
b10 .
b100 &
b100 -
b10 ,
b100 '
b100 +
b10 *
b1110 "
b1110 #
b1110 4
#75000
b1000000000000000 !
b1000000000000000 )
b1000 $
b1000 1
b11 0
b1000 %
b1000 /
b11 .
b1000 &
b1000 -
b11 ,
b1000 '
b1000 +
b11 *
b1111 "
b1111 #
b1111 4
#80000
b10000 4
