COA/bin/dff.v
module dff (
    input d,
    input clk,
    output reg q,
    output wire qbar
);

    always @(posedge clk)begin
        q <= d;
    end
    assign qbar = ~q;
    
endmodule

COA/bin/dff_tb.v
`timescale 1ns/1ps
module dff_tb;
    reg d, clk;
    wire q, qbar;

    dff uut(.d(d), .clk(clk), .q(q), .qbar(qbar));

    initial clk = 0;
    always #5 clk = ~clk;

    initial begin
        $dumpfile("dff.vcd");
        $dumpvars(0, dff_tb);
        $monitor("t = %0t clk = %b d = %b -> q = %b qbar = %b", $time, clk, d, q, qbar);

        d = 0;

        for(integer i = 0; i < 8; i++)begin
            #10; d = ~d;
        end
        #10;
        $finish;
    end

endmodule

COA/bin/dff.vcd
$date
	Mon Sep 15 09:52:10 2025
$end
$version
	Icarus Verilog
$end
$timescale
	1ps
$end
$scope module dff_tb $end
$var wire 1 ! qbar $end
$var wire 1 " q $end
$var reg 1 # clk $end
$var reg 1 $ d $end
$scope module uut $end
$var wire 1 # clk $end
$var wire 1 $ d $end
$var wire 1 ! qbar $end
$var reg 1 " q $end
$upscope $end
$scope begin $ivl_for_loop0 $end
$var integer 32 % i [31:0] $end
$upscope $end
$upscope $end
$enddefinitions $end
#0
$dumpvars
b0 %
0$
0#
x"
x!
$end
#5000
1!
0"
1#
#10000
0#
b1 %
1$
#15000
0!
1"
1#
#20000
0#
b10 %
0$
#25000
1!
0"
1#
#30000
0#
b11 %
1$
#35000
0!
1"
1#
#40000
0#
b100 %
0$
#45000
1!
0"
1#
#50000
0#
b101 %
1$
#55000
0!
1"
1#
#60000
0#
b110 %
0$
#65000
1!
0"
1#
#70000
0#
b111 %
1$
#75000
0!
1"
1#
#80000
0#
b1000 %
0$
#85000
1!
0"
1#
