COA/bin/fourbitadd.v
module fourbitadder(
    input  [3:0] A,
    input  [3:0] B,
    input        Cin,
    output [3:0] Sum,
    output       Cout
);
    assign {Cout, Sum} = A + B + Cin;
    endmodule

COA/bin/fourbitadd_tb.v
`timescale 1ns/1ps
module fourbitadder_tb;
    reg [3:0] A, B; 
    reg Cin;
    wire [3:0] Sum;
    wire Cout;
    fourbitadder uut(.A(A), .B(B), .Cin(Cin), .Sum(Sum), .Cout(Cout));
    initial begin
        A = 0; B = 0; Cin = 0;
        end

    initial begin

    $dumpfile("fourbitadd.vcd");
    $dumpvars(0, fourbitadder_tb);
    $monitor("t=%0t A=%b B=%b Cin=%b  |  Sum=%b Cout=%b", $time, A, B, Cin, Sum, Cout);

        for(integer i = 0; i < 16; i++) begin
            for(integer j = 0; j < 16; j++)begin
                for(integer k = 0; k < 2; k++)begin
                    A = i; B = j; Cin = k;
                    #5;
                    end
            end
        end

        end
endmodule

COA/bin/fourbitadd.vcd
$date
	Sun Sep 14 22:32:15 2025
$end
$version
	Icarus Verilog
$end
$timescale
	1ps
$end
$scope module fourbitadder_tb $end
$var wire 4 ! Sum [3:0] $end
$var wire 1 " Cout $end
$var reg 4 # A [3:0] $end
$var reg 4 $ B [3:0] $end
$var reg 1 % Cin $end
$scope module uut $end
$var wire 4 & A [3:0] $end
$var wire 4 ' B [3:0] $end
$var wire 1 % Cin $end
$var wire 4 ( Sum [3:0] $end
$var wire 1 " Cout $end
$upscope $end
$scope begin $ivl_for_loop0 $end
$var integer 32 ) i [31:0] $end
$scope begin $ivl_for_loop1 $end
$var integer 32 * j [31:0] $end
$scope begin $ivl_for_loop2 $end
$var integer 32 + k [31:0] $end
$upscope $end
$upscope $end
$upscope $end
$upscope $end
$enddefinitions $end
#0
$dumpvars
b0 +
b0 *
b0 )
b0 (
b0 '
b0 &
0%
b0 $
b0 #
0"
b0 !
$end
#5000
b1 !
b1 (
1%
b1 +
#10000
0%
b1 $
b1 '
b1 *
b0 +
#15000
b10 !
b10 (
1%
b1 +
#20000
0%
b10 $
b10 '
b10 *
b0 +
#25000
b11 !
b11 (
1%
b1 +
#30000
0%
b11 $
b11 '
b11 *
b0 +
#35000
b100 !
b100 (
1%
b1 +
#40000
0%
b100 $
b100 '
b100 *
b0 +
#45000
b101 !
b101 (
1%
b1 +
#50000
0%
b101 $
b101 '
b101 *
b0 +
#55000
b110 !
b110 (
1%
b1 +
#60000
0%
b110 $
b110 '
b110 *
b0 +
#65000
b111 !
b111 (
1%
b1 +
#70000
0%
b111 $
b111 '
b111 *
b0 +
#75000
b1000 !
b1000 (
1%
b1 +
#80000
0%
b1000 $
b1000 '
b1000 *
b0 +
#85000
b1001 !
b1001 (
1%
b1 +
#90000
0%
b1001 $
b1001 '
b1001 *
b0 +
#95000
b1010 !
b1010 (
1%
b1 +
#100000
0%
b1010 $
b1010 '
b1010 *
b0 +
#105000
b1011 !
b1011 (
1%
b1 +
#110000
0%
b1011 $
b1011 '
b1011 *
b0 +
#115000
b1100 !
b1100 (
1%
b1 +
#120000
0%
b1100 $
b1100 '
b1100 *
b0 +
#125000
b1101 !
b1101 (
1%
b1 +
#130000
0%
b1101 $
b1101 '
b1101 *
b0 +
#135000
b1110 !
b1110 (
1%
b1 +
#140000
0%
b1110 $
b1110 '
b1110 *
b0 +
#145000
b1111 !
b1111 (
1%
b1 +
#150000
0%
b1111 $
b1111 '
b1111 *
b0 +
#155000
b0 !
b0 (
1"
1%
b1 +
#160000
0"
b1 !
b1 (
0%
b0 $
b0 '
b1 #
b1 &
b1 )
b0 *
b0 +
#165000
b10 !
b10 (
1%
b1 +
#170000
0%
b1 $
b1 '
b1 *
b0 +
#175000
b11 !
b11 (
1%
b1 +
#180000
0%
b10 $
b10 '
b10 *
b0 +
#185000
b100 !
b100 (
1%
b1 +
#190000
0%
b11 $
b11 '
b11 *
b0 +
#195000
b101 !
b101 (
1%
b1 +
#200000
0%
b100 $
b100 '
b100 *
b0 +
#205000
b110 !
b110 (
1%
b1 +
#210000
0%
b101 $
b101 '
b101 *
b0 +
#215000
b111 !
b111 (
1%
b1 +
#220000
0%
b110 $
b110 '
b110 *
b0 +
#225000
b1000 !
b1000 (
1%
b1 +
#230000
0%
b111 $
b111 '
b111 *
b0 +
#235000
b1001 !
b1001 (
1%
b1 +
#240000
0%
b1000 $
b1000 '
b1000 *
b0 +
#245000
b1010 !
b1010 (
1%
b1 +
#250000
0%
b1001 $
b1001 '
b1001 *
b0 +
#255000
b1011 !
b1011 (
1%
b1 +
#260000
0%
b1010 $
b1010 '
b1010 *
b0 +
#265000
b1100 !
b1100 (
1%
b1 +
#270000
0%
b1011 $
b1011 '
b1011 *
b0 +
#275000
b1101 !
b1101 (
1%
b1 +
#280000
0%
b1100 $
b1100 '
b1100 *
b0 +
#285000
b1110 !
b1110 (
1%
b1 +
#290000
0%
b1101 $
b1101 '
b1101 *
b0 +
#295000
b1111 !
b1111 (
1%
b1 +
#300000
0%
b1110 $
b1110 '
b1110 *
b0 +
#305000
b0 !
b0 (
1"
1%
b1 +
#310000
0%
b1111 $
b1111 '
b1111 *
b0 +
#315000
b1 !
b1 (
1%
b1 +
#320000
0"
b10 !
b10 (
0%
b0 $
b0 '
b10 #
b10 &
b10 )
b0 *
b0 +
#325000
b11 !
b11 (
1%
b1 +
#330000
0%
b1 $
b1 '
b1 *
b0 +
#335000
b100 !
b100 (
1%
b1 +
#340000
0%
b10 $
b10 '
b10 *
b0 +
#345000
b101 !
b101 (
1%
b1 +
#350000
0%
b11 $
b11 '
b11 *
b0 +
#355000
b110 !
b110 (
1%
b1 +
#360000
0%
b100 $
b100 '
b100 *
b0 +
#365000
b111 !
b111 (
1%
b1 +
#370000
0%
b101 $
b101 '
b101 *
b0 +
#375000
b1000 !
b1000 (
1%
b1 +
#380000
0%
b110 $
b110 '
b110 *
b0 +
#385000
b1001 !
b1001 (
1%
b1 +
#390000
0%
b111 $
b111 '
b111 *
b0 +
#395000
b1010 !
b1010 (
1%
b1 +
#400000
0%
b1000 $
b1000 '
b1000 *
b0 +
#405000
b1011 !
b1011 (
1%
b1 +
#410000
0%
b1001 $
b1001 '
b1001 *
b0 +
#415000
b1100 !
b1100 (
1%
b1 +
#420000
0%
b1010 $
b1010 '
b1010 *
b0 +
#425000
b1101 !
b1101 (
1%
b1 +
#430000
0%
b1011 $
b1011 '
b1011 *
b0 +
#435000
b1110 !
b1110 (
1%
b1 +
#440000
0%
b1100 $
b1100 '
b1100 *
b0 +
#445000
b1111 !
b1111 (
1%
b1 +
#450000
0%
b1101 $
b1101 '
b1101 *
b0 +
#455000
b0 !
b0 (
1"
1%
b1 +
#460000
0%
b1110 $
b1110 '
b1110 *
b0 +
#465000
b1 !
b1 (
1%
b1 +
#470000
0%
b1111 $
b1111 '
b1111 *
b0 +
#475000
b10 !
b10 (
1%
b1 +
#480000
0"
b11 !
b11 (
0%
b0 $
b0 '
b11 #
b11 &
b11 )
b0 *
b0 +
#485000
b100 !
b100 (
1%
b1 +
#490000
0%
b1 $
b1 '
b1 *
b0 +
#495000
b101 !
b101 (
1%
b1 +
#500000
0%
b10 $
b10 '
b10 *
b0 +
#505000
b110 !
b110 (
1%
b1 +
#510000
0%
b11 $
b11 '
b11 *
b0 +
#515000
b111 !
b111 (
1%
b1 +
#520000
0%
b100 $
b100 '
b100 *
b0 +
#525000
b1000 !
b1000 (
1%
b1 +
#530000
0%
b101 $
b101 '
b101 *
b0 +
#535000
b1001 !
b1001 (
1%
b1 +
#540000
0%
b110 $
b110 '
b110 *
b0 +
#545000
b1010 !
b1010 (
1%
b1 +
#550000
0%
b111 $
b111 '
b111 *
b0 +
#555000
b1011 !
b1011 (
1%
b1 +
#560000
0%
b1000 $
b1000 '
b1000 *
b0 +
#565000
b1100 !
b1100 (
1%
b1 +
#570000
0%
b1001 $
b1001 '
b1001 *
b0 +
#575000
b1101 !
b1101 (
1%
b1 +
#580000
0%
b1010 $
b1010 '
b1010 *
b0 +
#585000
b1110 !
b1110 (
1%
b1 +
#590000
0%
b1011 $
b1011 '
b1011 *
b0 +
#595000
b1111 !
b1111 (
1%
b1 +
#600000
0%
b1100 $
b1100 '
b1100 *
b0 +
#605000
b0 !
b0 (
1"
1%
b1 +
#610000
0%
b1101 $
b1101 '
b1101 *
b0 +
#615000
b1 !
b1 (
1%
b1 +
#620000
0%
b1110 $
b1110 '
b1110 *
b0 +
#625000
b10 !
b10 (
1%
b1 +
#630000
0%
b1111 $
b1111 '
b1111 *
b0 +
#635000
b11 !
b11 (
1%
b1 +
#640000
0"
b100 !
b100 (
0%
b0 $
b0 '
b100 #
b100 &
b100 )
b0 *
b0 +
#645000
b101 !
b101 (
1%
b1 +
#650000
0%
b1 $
b1 '
b1 *
b0 +
#655000
b110 !
b110 (
1%
b1 +
#660000
0%
b10 $
b10 '
b10 *
b0 +
#665000
b111 !
b111 (
1%
b1 +
#670000
0%
b11 $
b11 '
b11 *
b0 +
#675000
b1000 !
b1000 (
1%
b1 +
#680000
0%
b100 $
b100 '
b100 *
b0 +
#685000
b1001 !
b1001 (
1%
b1 +
#690000
0%
b101 $
b101 '
b101 *
b0 +
#695000
b1010 !
b1010 (
1%
b1 +
#700000
0%
b110 $
b110 '
b110 *
b0 +
#705000
b1011 !
b1011 (
1%
b1 +
#710000
0%
b111 $
b111 '
b111 *
b0 +
#715000
b1100 !
b1100 (
1%
b1 +
#720000
0%
b1000 $
b1000 '
b1000 *
b0 +
#725000
b1101 !
b1101 (
1%
b1 +
#730000
0%
b1001 $
b1001 '
b1001 *
b0 +
#735000
b1110 !
b1110 (
1%
b1 +
#740000
0%
b1010 $
b1010 '
b1010 *
b0 +
#745000
b1111 !
b1111 (
1%
b1 +
#750000
0%
b1011 $
b1011 '
b1011 *
b0 +
#755000
b0 !
b0 (
1"
1%
b1 +
#760000
0%
b1100 $
b1100 '
b1100 *
b0 +
#765000
b1 !
b1 (
1%
b1 +
#770000
0%
b1101 $
b1101 '
b1101 *
b0 +
#775000
b10 !
b10 (
1%
b1 +
#780000
0%
b1110 $
b1110 '
b1110 *
b0 +
#785000
b11 !
b11 (
1%
b1 +
#790000
0%
b1111 $
b1111 '
b1111 *
b0 +
#795000
b100 !
b100 (
1%
b1 +
#800000
0"
b101 !
b101 (
0%
b0 $
b0 '
b101 #
b101 &
b101 )
b0 *
b0 +
#805000
b110 !
b110 (
1%
b1 +
#810000
0%
b1 $
b1 '
b1 *
b0 +
#815000
b111 !
b111 (
1%
b1 +
#820000
0%
b10 $
b10 '
b10 *
b0 +
#825000
b1000 !
b1000 (
1%
b1 +
#830000
0%
b11 $
b11 '
b11 *
b0 +
#835000
b1001 !
b1001 (
1%
b1 +
#840000
0%
b100 $
b100 '
b100 *
b0 +
#845000
b1010 !
b1010 (
1%
b1 +
#850000
0%
b101 $
b101 '
b101 *
b0 +
#855000
b1011 !
b1011 (
1%
b1 +
#860000
0%
b110 $
b110 '
b110 *
b0 +
#865000
b1100 !
b1100 (
1%
b1 +
#870000
0%
b111 $
b111 '
b111 *
b0 +
#875000
b1101 !
b1101 (
1%
b1 +
#880000
0%
b1000 $
b1000 '
b1000 *
b0 +
#885000
b1110 !
b1110 (
1%
b1 +
#890000
0%
b1001 $
b1001 '
b1001 *
b0 +
#895000
b1111 !
b1111 (
1%
b1 +
#900000
0%
b1010 $
b1010 '
b1010 *
b0 +
#905000
b0 !
b0 (
1"
1%
b1 +
#910000
0%
b1011 $
b1011 '
b1011 *
b0 +
#915000
b1 !
b1 (
1%
b1 +
#920000
0%
b1100 $
b1100 '
b1100 *
b0 +
#925000
b10 !
b10 (
1%
b1 +
#930000
0%
b1101 $
b1101 '
b1101 *
b0 +
#935000
b11 !
b11 (
1%
b1 +
#940000
0%
b1110 $
b1110 '
b1110 *
b0 +
#945000
b100 !
b100 (
1%
b1 +
#950000
0%
b1111 $
b1111 '
b1111 *
b0 +
#955000
b101 !
b101 (
1%
b1 +
#960000
0"
b110 !
b110 (
0%
b0 $
b0 '
b110 #
b110 &
b110 )
b0 *
b0 +
#965000
b111 !
b111 (
1%
b1 +
#970000
0%
b1 $
b1 '
b1 *
b0 +
#975000
b1000 !
b1000 (
1%
b1 +
#980000
0%
b10 $
b10 '
b10 *
b0 +
#985000
b1001 !
b1001 (
1%
b1 +
#990000
0%
b11 $
b11 '
b11 *
b0 +
#995000
b1010 !
b1010 (
1%
b1 +
#1000000
0%
b100 $
b100 '
b100 *
b0 +
#1005000
b1011 !
b1011 (
1%
b1 +
#1010000
0%
b101 $
b101 '
b101 *
b0 +
#1015000
b1100 !
b1100 (
1%
b1 +
#1020000
0%
b110 $
b110 '
b110 *
b0 +
#1025000
b1101 !
b1101 (
1%
b1 +
#1030000
0%
b111 $
b111 '
b111 *
b0 +
#1035000
b1110 !
b1110 (
1%
b1 +
#1040000
0%
b1000 $
b1000 '
b1000 *
b0 +
#1045000
b1111 !
b1111 (
1%
b1 +
#1050000
0%
b1001 $
b1001 '
b1001 *
b0 +
#1055000
b0 !
b0 (
1"
1%
b1 +
#1060000
0%
b1010 $
b1010 '
b1010 *
b0 +
#1065000
b1 !
b1 (
1%
b1 +
#1070000
0%
b1011 $
b1011 '
b1011 *
b0 +
#1075000
b10 !
b10 (
1%
b1 +
#1080000
0%
b1100 $
b1100 '
b1100 *
b0 +
#1085000
b11 !
b11 (
1%
b1 +
#1090000
0%
b1101 $
b1101 '
b1101 *
b0 +
#1095000
b100 !
b100 (
1%
b1 +
#1100000
0%
b1110 $
b1110 '
b1110 *
b0 +
#1105000
b101 !
b101 (
1%
b1 +
#1110000
0%
b1111 $
b1111 '
b1111 *
b0 +
#1115000
b110 !
b110 (
1%
b1 +
#1120000
0"
b111 !
b111 (
0%
b0 $
b0 '
b111 #
b111 &
b111 )
b0 *
b0 +
#1125000
b1000 !
b1000 (
1%
b1 +
#1130000
0%
b1 $
b1 '
b1 *
b0 +
#1135000
b1001 !
b1001 (
1%
b1 +
#1140000
0%
b10 $
b10 '
b10 *
b0 +
#1145000
b1010 !
b1010 (
1%
b1 +
#1150000
0%
b11 $
b11 '
b11 *
b0 +
#1155000
b1011 !
b1011 (
1%
b1 +
#1160000
0%
b100 $
b100 '
b100 *
b0 +
#1165000
b1100 !
b1100 (
1%
b1 +
#1170000
0%
b101 $
b101 '
b101 *
b0 +
#1175000
b1101 !
b1101 (
1%
b1 +
#1180000
0%
b110 $
b110 '
b110 *
b0 +
#1185000
b1110 !
b1110 (
1%
b1 +
#1190000
0%
b111 $
b111 '
b111 *
b0 +
#1195000
b1111 !
b1111 (
1%
b1 +
#1200000
0%
b1000 $
b1000 '
b1000 *
b0 +
#1205000
b0 !
b0 (
1"
1%
b1 +
#1210000
0%
b1001 $
b1001 '
b1001 *
b0 +
#1215000
b1 !
b1 (
1%
b1 +
#1220000
0%
b1010 $
b1010 '
b1010 *
b0 +
#1225000
b10 !
b10 (
1%
b1 +
#1230000
0%
b1011 $
b1011 '
b1011 *
b0 +
#1235000
b11 !
b11 (
1%
b1 +
#1240000
0%
b1100 $
b1100 '
b1100 *
b0 +
#1245000
b100 !
b100 (
1%
b1 +
#1250000
0%
b1101 $
b1101 '
b1101 *
b0 +
#1255000
b101 !
b101 (
1%
b1 +
#1260000
0%
b1110 $
b1110 '
b1110 *
b0 +
#1265000
b110 !
b110 (
1%
b1 +
#1270000
0%
b1111 $
b1111 '
b1111 *
b0 +
#1275000
b111 !
b111 (
1%
b1 +
#1280000
0"
b1000 !
b1000 (
0%
b0 $
b0 '
b1000 #
b1000 &
b1000 )
b0 *
b0 +
#1285000
b1001 !
b1001 (
1%
b1 +
#1290000
0%
b1 $
b1 '
b1 *
b0 +
#1295000
b1010 !
b1010 (
1%
b1 +
#1300000
0%
b10 $
b10 '
b10 *
b0 +
#1305000
b1011 !
b1011 (
1%
b1 +
#1310000
0%
b11 $
b11 '
b11 *
b0 +
#1315000
b1100 !
b1100 (
1%
b1 +
#1320000
0%
b100 $
b100 '
b100 *
b0 +
#1325000
b1101 !
b1101 (
1%
b1 +
#1330000
0%
b101 $
b101 '
b101 *
b0 +
#1335000
b1110 !
b1110 (
1%
b1 +
#1340000
0%
b110 $
b110 '
b110 *
b0 +
#1345000
b1111 !
b1111 (
1%
b1 +
#1350000
0%
b111 $
b111 '
b111 *
b0 +
#1355000
b0 !
b0 (
1"
1%
b1 +
#1360000
0%
b1000 $
b1000 '
b1000 *
b0 +
#1365000
b1 !
b1 (
1%
b1 +
#1370000
0%
b1001 $
b1001 '
b1001 *
b0 +
#1375000
b10 !
b10 (
1%
b1 +
#1380000
0%
b1010 $
b1010 '
b1010 *
b0 +
#1385000
b11 !
b11 (
1%
b1 +
#1390000
0%
b1011 $
b1011 '
b1011 *
b0 +
#1395000
b100 !
b100 (
1%
b1 +
#1400000
0%
b1100 $
b1100 '
b1100 *
b0 +
#1405000
b101 !
b101 (
1%
b1 +
#1410000
0%
b1101 $
b1101 '
b1101 *
b0 +
#1415000
b110 !
b110 (
1%
b1 +
#1420000
0%
b1110 $
b1110 '
b1110 *
b0 +
#1425000
b111 !
b111 (
1%
b1 +
#1430000
0%
b1111 $
b1111 '
b1111 *
b0 +
#1435000
b1000 !
b1000 (
1%
b1 +
#1440000
0"
b1001 !
b1001 (
0%
b0 $
b0 '
b1001 #
b1001 &
b1001 )
b0 *
b0 +
#1445000
b1010 !
b1010 (
1%
b1 +
#1450000
0%
b1 $
b1 '
b1 *
b0 +
#1455000
b1011 !
b1011 (
1%
b1 +
#1460000
0%
b10 $
b10 '
b10 *
b0 +
#1465000
b1100 !
b1100 (
1%
b1 +
#1470000
0%
b11 $
b11 '
b11 *
b0 +
#1475000
b1101 !
b1101 (
1%
b1 +
#1480000
0%
b100 $
b100 '
b100 *
b0 +
#1485000
b1110 !
b1110 (
1%
b1 +
#1490000
0%
b101 $
b101 '
b101 *
b0 +
#1495000
b1111 !
b1111 (
1%
b1 +
#1500000
0%
b110 $
b110 '
b110 *
b0 +
#1505000
b0 !
b0 (
1"
1%
b1 +
#1510000
0%
b111 $
b111 '
b111 *
b0 +
#1515000
b1 !
b1 (
1%
b1 +
#1520000
0%
b1000 $
b1000 '
b1000 *
b0 +
#1525000
b10 !
b10 (
1%
b1 +
#1530000
0%
b1001 $
b1001 '
b1001 *
b0 +
#1535000
b11 !
b11 (
1%
b1 +
#1540000
0%
b1010 $
b1010 '
b1010 *
b0 +
#1545000
b100 !
b100 (
1%
b1 +
#1550000
0%
b1011 $
b1011 '
b1011 *
b0 +
#1555000
b101 !
b101 (
1%
b1 +
#1560000
0%
b1100 $
b1100 '
b1100 *
b0 +
#1565000
b110 !
b110 (
1%
b1 +
#1570000
0%
b1101 $
b1101 '
b1101 *
b0 +
#1575000
b111 !
b111 (
1%
b1 +
#1580000
0%
b1110 $
b1110 '
b1110 *
b0 +
#1585000
b1000 !
b1000 (
1%
b1 +
#1590000
0%
b1111 $
b1111 '
b1111 *
b0 +
#1595000
b1001 !
b1001 (
1%
b1 +
#1600000
0"
b1010 !
b1010 (
0%
b0 $
b0 '
b1010 #
b1010 &
b1010 )
b0 *
b0 +
#1605000
b1011 !
b1011 (
1%
b1 +
#1610000
0%
b1 $
b1 '
b1 *
b0 +
#1615000
b1100 !
b1100 (
1%
b1 +
#1620000
0%
b10 $
b10 '
b10 *
b0 +
#1625000
b1101 !
b1101 (
1%
b1 +
#1630000
0%
b11 $
b11 '
b11 *
b0 +
#1635000
b1110 !
b1110 (
1%
b1 +
#1640000
0%
b100 $
b100 '
b100 *
b0 +
#1645000
b1111 !
b1111 (
1%
b1 +
#1650000
0%
b101 $
b101 '
b101 *
b0 +
#1655000
b0 !
b0 (
1"
1%
b1 +
#1660000
0%
b110 $
b110 '
b110 *
b0 +
#1665000
b1 !
b1 (
1%
b1 +
#1670000
0%
b111 $
b111 '
b111 *
b0 +
#1675000
b10 !
b10 (
1%
b1 +
#1680000
0%
b1000 $
b1000 '
b1000 *
b0 +
#1685000
b11 !
b11 (
1%
b1 +
#1690000
0%
b1001 $
b1001 '
b1001 *
b0 +
#1695000
b100 !
b100 (
1%
b1 +
#1700000
0%
b1010 $
b1010 '
b1010 *
b0 +
#1705000
b101 !
b101 (
1%
b1 +
#1710000
0%
b1011 $
b1011 '
b1011 *
b0 +
#1715000
b110 !
b110 (
1%
b1 +
#1720000
0%
b1100 $
b1100 '
b1100 *
b0 +
#1725000
b111 !
b111 (
1%
b1 +
#1730000
0%
b1101 $
b1101 '
b1101 *
b0 +
#1735000
b1000 !
b1000 (
1%
b1 +
#1740000
0%
b1110 $
b1110 '
b1110 *
b0 +
#1745000
b1001 !
b1001 (
1%
b1 +
#1750000
0%
b1111 $
b1111 '
b1111 *
b0 +
#1755000
b1010 !
b1010 (
1%
b1 +
#1760000
0"
b1011 !
b1011 (
0%
b0 $
b0 '
b1011 #
b1011 &
b1011 )
b0 *
b0 +
#1765000
b1100 !
b1100 (
1%
b1 +
#1770000
0%
b1 $
b1 '
b1 *
b0 +
#1775000
b1101 !
b1101 (
1%
b1 +
#1780000
0%
b10 $
b10 '
b10 *
b0 +
#1785000
b1110 !
b1110 (
1%
b1 +
#1790000
0%
b11 $
b11 '
b11 *
b0 +
#1795000
b1111 !
b1111 (
1%
b1 +
#1800000
0%
b100 $
b100 '
b100 *
b0 +
#1805000
b0 !
b0 (
1"
1%
b1 +
#1810000
0%
b101 $
b101 '
b101 *
b0 +
#1815000
b1 !
b1 (
1%
b1 +
#1820000
0%
b110 $
b110 '
b110 *
b0 +
#1825000
b10 !
b10 (
1%
b1 +
#1830000
0%
b111 $
b111 '
b111 *
b0 +
#1835000
b11 !
b11 (
1%
b1 +
#1840000
0%
b1000 $
b1000 '
b1000 *
b0 +
#1845000
b100 !
b100 (
1%
b1 +
#1850000
0%
b1001 $
b1001 '
b1001 *
b0 +
#1855000
b101 !
b101 (
1%
b1 +
#1860000
0%
b1010 $
b1010 '
b1010 *
b0 +
#1865000
b110 !
b110 (
1%
b1 +
#1870000
0%
b1011 $
b1011 '
b1011 *
b0 +
#1875000
b111 !
b111 (
1%
b1 +
#1880000
0%
b1100 $
b1100 '
b1100 *
b0 +
#1885000
b1000 !
b1000 (
1%
b1 +
#1890000
0%
b1101 $
b1101 '
b1101 *
b0 +
#1895000
b1001 !
b1001 (
1%
b1 +
#1900000
0%
b1110 $
b1110 '
b1110 *
b0 +
#1905000
b1010 !
b1010 (
1%
b1 +
#1910000
0%
b1111 $
b1111 '
b1111 *
b0 +
#1915000
b1011 !
b1011 (
1%
b1 +
#1920000
0"
b1100 !
b1100 (
0%
b0 $
b0 '
b1100 #
b1100 &
b1100 )
b0 *
b0 +
#1925000
b1101 !
b1101 (
1%
b1 +
#1930000
0%
b1 $
b1 '
b1 *
b0 +
#1935000
b1110 !
b1110 (
1%
b1 +
#1940000
0%
b10 $
b10 '
b10 *
b0 +
#1945000
b1111 !
b1111 (
1%
b1 +
#1950000
0%
b11 $
b11 '
b11 *
b0 +
#1955000
b0 !
b0 (
1"
1%
b1 +
#1960000
0%
b100 $
b100 '
b100 *
b0 +
#1965000
b1 !
b1 (
1%
b1 +
#1970000
0%
b101 $
b101 '
b101 *
b0 +
#1975000
b10 !
b10 (
1%
b1 +
#1980000
0%
b110 $
b110 '
b110 *
b0 +
#1985000
b11 !
b11 (
1%
b1 +
#1990000
0%
b111 $
b111 '
b111 *
b0 +
#1995000
b100 !
b100 (
1%
b1 +
#2000000
0%
b1000 $
b1000 '
b1000 *
b0 +
#2005000
b101 !
b101 (
1%
b1 +
#2010000
0%
b1001 $
b1001 '
b1001 *
b0 +
#2015000
b110 !
b110 (
1%
b1 +
#2020000
0%
b1010 $
b1010 '
b1010 *
b0 +
#2025000
b111 !
b111 (
1%
b1 +
#2030000
0%
b1011 $
b1011 '
b1011 *
b0 +
#2035000
b1000 !
b1000 (
1%
b1 +
#2040000
0%
b1100 $
b1100 '
b1100 *
b0 +
#2045000
b1001 !
b1001 (
1%
b1 +
#2050000
0%
b1101 $
b1101 '
b1101 *
b0 +
#2055000
b1010 !
b1010 (
1%
b1 +
#2060000
0%
b1110 $
b1110 '
b1110 *
b0 +
#2065000
b1011 !
b1011 (
1%
b1 +
#2070000
0%
b1111 $
b1111 '
b1111 *
b0 +
#2075000
b1100 !
b1100 (
1%
b1 +
#2080000
0"
b1101 !
b1101 (
0%
b0 $
b0 '
b1101 #
b1101 &
b1101 )
b0 *
b0 +
#2085000
b1110 !
b1110 (
1%
b1 +
#2090000
0%
b1 $
b1 '
b1 *
b0 +
#2095000
b1111 !
b1111 (
1%
b1 +
#2100000
0%
b10 $
b10 '
b10 *
b0 +
#2105000
b0 !
b0 (
1"
1%
b1 +
#2110000
0%
b11 $
b11 '
b11 *
b0 +
#2115000
b1 !
b1 (
1%
b1 +
#2120000
0%
b100 $
b100 '
b100 *
b0 +
#2125000
b10 !
b10 (
1%
b1 +
#2130000
0%
b101 $
b101 '
b101 *
b0 +
#2135000
b11 !
b11 (
1%
b1 +
#2140000
0%
b110 $
b110 '
b110 *
b0 +
#2145000
b100 !
b100 (
1%
b1 +
#2150000
0%
b111 $
b111 '
b111 *
b0 +
#2155000
b101 !
b101 (
1%
b1 +
#2160000
0%
b1000 $
b1000 '
b1000 *
b0 +
#2165000
b110 !
b110 (
1%
b1 +
#2170000
0%
b1001 $
b1001 '
b1001 *
b0 +
#2175000
b111 !
b111 (
1%
b1 +
#2180000
0%
b1010 $
b1010 '
b1010 *
b0 +
#2185000
b1000 !
b1000 (
1%
b1 +
#2190000
0%
b1011 $
b1011 '
b1011 *
b0 +
#2195000
b1001 !
b1001 (
1%
b1 +
#2200000
0%
b1100 $
b1100 '
b1100 *
b0 +
#2205000
b1010 !
b1010 (
1%
b1 +
#2210000
0%
b1101 $
b1101 '
b1101 *
b0 +
#2215000
b1011 !
b1011 (
1%
b1 +
#2220000
0%
b1110 $
b1110 '
b1110 *
b0 +
#2225000
b1100 !
b1100 (
1%
b1 +
#2230000
0%
b1111 $
b1111 '
b1111 *
b0 +
#2235000
b1101 !
b1101 (
1%
b1 +
#2240000
0"
b1110 !
b1110 (
0%
b0 $
b0 '
b1110 #
b1110 &
b1110 )
b0 *
b0 +
#2245000
b1111 !
b1111 (
1%
b1 +
#2250000
0%
b1 $
b1 '
b1 *
b0 +
#2255000
b0 !
b0 (
1"
1%
b1 +
#2260000
0%
b10 $
b10 '
b10 *
b0 +
#2265000
b1 !
b1 (
1%
b1 +
#2270000
0%
b11 $
b11 '
b11 *
b0 +
#2275000
b10 !
b10 (
1%
b1 +
#2280000
0%
b100 $
b100 '
b100 *
b0 +
#2285000
b11 !
b11 (
1%
b1 +
#2290000
0%
b101 $
b101 '
b101 *
b0 +
#2295000
b100 !
b100 (
1%
b1 +
#2300000
0%
b110 $
b110 '
b110 *
b0 +
#2305000
b101 !
b101 (
1%
b1 +
#2310000
0%
b111 $
b111 '
b111 *
b0 +
#2315000
b110 !
b110 (
1%
b1 +
#2320000
0%
b1000 $
b1000 '
b1000 *
b0 +
#2325000
b111 !
b111 (
1%
b1 +
#2330000
0%
b1001 $
b1001 '
b1001 *
b0 +
#2335000
b1000 !
b1000 (
1%
b1 +
#2340000
0%
b1010 $
b1010 '
b1010 *
b0 +
#2345000
b1001 !
b1001 (
1%
b1 +
#2350000
0%
b1011 $
b1011 '
b1011 *
b0 +
#2355000
b1010 !
b1010 (
1%
b1 +
#2360000
0%
b1100 $
b1100 '
b1100 *
b0 +
#2365000
b1011 !
b1011 (
1%
b1 +
#2370000
0%
b1101 $
b1101 '
b1101 *
b0 +
#2375000
b1100 !
b1100 (
1%
b1 +
#2380000
0%
b1110 $
b1110 '
b1110 *
b0 +
#2385000
b1101 !
b1101 (
1%
b1 +
#2390000
0%
b1111 $
b1111 '
b1111 *
b0 +
#2395000
b1110 !
b1110 (
1%
b1 +
#2400000
0"
b1111 !
b1111 (
0%
b0 $
b0 '
b1111 #
b1111 &
b1111 )
b0 *
b0 +
#2405000
b0 !
b0 (
1"
1%
b1 +
#2410000
0%
b1 $
b1 '
b1 *
b0 +
#2415000
b1 !
b1 (
1%
b1 +
#2420000
0%
b10 $
b10 '
b10 *
b0 +
#2425000
b10 !
b10 (
1%
b1 +
#2430000
0%
b11 $
b11 '
b11 *
b0 +
#2435000
b11 !
b11 (
1%
b1 +
#2440000
0%
b100 $
b100 '
b100 *
b0 +
#2445000
b100 !
b100 (
1%
b1 +
#2450000
0%
b101 $
b101 '
b101 *
b0 +
#2455000
b101 !
b101 (
1%
b1 +
#2460000
0%
b110 $
b110 '
b110 *
b0 +
#2465000
b110 !
b110 (
1%
b1 +
#2470000
0%
b111 $
b111 '
b111 *
b0 +
#2475000
b111 !
b111 (
1%
b1 +
#2480000
0%
b1000 $
b1000 '
b1000 *
b0 +
#2485000
b1000 !
b1000 (
1%
b1 +
#2490000
0%
b1001 $
b1001 '
b1001 *
b0 +
#2495000
b1001 !
b1001 (
1%
b1 +
#2500000
0%
b1010 $
b1010 '
b1010 *
b0 +
#2505000
b1010 !
b1010 (
1%
b1 +
#2510000
0%
b1011 $
b1011 '
b1011 *
b0 +
#2515000
b1011 !
b1011 (
1%
b1 +
#2520000
0%
b1100 $
b1100 '
b1100 *
b0 +
#2525000
b1100 !
b1100 (
1%
b1 +
#2530000
0%
b1101 $
b1101 '
b1101 *
b0 +
#2535000
b1101 !
b1101 (
1%
b1 +
#2540000
0%
b1110 $
b1110 '
b1110 *
b0 +
#2545000
b1110 !
b1110 (
1%
b1 +
#2550000
0%
b1111 $
b1111 '
b1111 *
b0 +
#2555000
b1111 !
b1111 (
1%
b1 +
#2560000
b10000 )
b10000 *
b10 +
