COA/bin/mux8x1.v
module mux8x1 (
    input s2, s1, s0, enable,
    input [7:0] I,
    output Y
);
    wire [7:0] w;

    assign w[7] = s2 & s1 & s0 & I[7];
    assign w[6] = s2 & s1 & ~s0 & I[6];
    assign w[5] = s2 & ~s1 & s0 & I[5];
    assign w[4] = s2 & ~s1 & ~s0 & I[4];
    assign w[3] = ~s2 & s1 & s0 & I[3];
    assign w[2] = ~s2 & s1 & ~s0 & I[2];
    assign w[1] = ~s2 & ~s1 & s0 & I[1];
    assign w[0] = ~s2 & ~s1 & ~s0 & I[0];

    assign Y = enable & (|w);
    
endmodule

COA/bin/mux8x1_tb.v
`timescale 1ns/1ps
module mux8x1_tb;
    reg s2, s1, s0, enable;
    reg [7:0] I;
    wire Y;

    mux8x1 uut(.s2(s2), .s1(s1), .s0(s0), .enable(enable), .I(I), .Y(Y));

    initial begin
        s2 = 0; s1 = 0; s0 = 0; 
        enable = 1; 
        I = 8'b0101_0110;
    end

    initial begin
        $dumpfile("mux8x1.vcd");
        $dumpvars(0, mux8x1_tb);
        $monitor("t = %0t sel = %b%b%b I = %b -> Y = %b", $time, s2, s1, s0, I, Y);

        for (integer i = 0; i < 8; i++) begin
            {s2, s1, s0} = i;
            #10;
        end
        $finish;
    end

endmodule

COA/bin/mux8x1.vcd
$date
	Mon Sep 15 09:02:51 2025
$end
$version
	Icarus Verilog
$end
$timescale
	1ps
$end
$scope module mux8x1_tb $end
$var wire 1 ! Y $end
$var reg 8 " I [7:0] $end
$var reg 1 # enable $end
$var reg 1 $ s0 $end
$var reg 1 % s1 $end
$var reg 1 & s2 $end
$scope module uut $end
$var wire 8 ' I [7:0] $end
$var wire 1 ! Y $end
$var wire 1 # enable $end
$var wire 1 $ s0 $end
$var wire 1 % s1 $end
$var wire 1 & s2 $end
$var wire 8 ( w [7:0] $end
$upscope $end
$scope begin $ivl_for_loop0 $end
$var integer 32 ) i [31:0] $end
$upscope $end
$upscope $end
$enddefinitions $end
#0
$dumpvars
b0 )
b0 (
b1010110 '
0&
0%
0$
1#
b1010110 "
0!
$end
#10000
1!
b10 (
1$
b1 )
#20000
1!
b100 (
1%
0$
b10 )
#30000
0!
b0 (
1$
b11 )
#40000
1!
b10000 (
1&
0%
0$
b100 )
#50000
0!
b0 (
1$
b101 )
#60000
1!
b1000000 (
1%
0$
b110 )
#70000
0!
b0 (
1$
b111 )
#80000
b1000 )
