COA/Dff.v
module Dff (
    input  wire clk,
    input  wire d,
    output reg  q,
    output wire qbar
);

    always @(posedge clk) begin
        q <= d;
    end

    assign qbar = ~q;

endmodule

COA/Dflipflop/Dff_tb.v
`timescale 1ns/1ps
module Dff_tb;

    reg clk, d;
    wire q, qbar;

    Dff uut (.clk(clk), .d(d), .q(q), .qbar(qbar));

    initial clk = 0;
    always #5 clk = ~clk;

    initial begin
        $dumpfile("Dff.vcd");
        $dumpvars(0, Dff_tb);
        $monitor("t=%0t D=%b Q=%b Qbar=%b clk=%b", $time, d, q, qbar, clk);
        d = 0; #10;
        d = 1; #10;
        d = 0; #10;
        d = 1; #10;

        $finish;
    end
endmodule

COA/Dff.vcd
$date
	Mon Sep 01 11:46:04 2025
$end
$version
	Icarus Verilog
$end
$timescale
	1ps
$end
$scope module Dff_tb $end
$var wire 1 ! qbar $end
$var wire 1 " q $end
$var reg 1 # clk $end
$var reg 1 $ d $end
$scope module uut $end
$var wire 1 # clk $end
$var wire 1 $ d $end
$var wire 1 ! qbar $end
$var reg 1 " q $end
$upscope $end
$upscope $end
$enddefinitions $end
#0
$dumpvars
0$
0#
x"
x!
$end
#5000
1!
0"
1#
#10000
0#
1$
#15000
0!
1"
1#
#20000
0#
0$
#25000
1!
0"
1#
#30000
0#
1$
#35000
0!
1"
1#
