COA/HA.v
module HA (input a, input b, output s, output c);
    xor gate_xor(s, a, b);
    and gate_and(c, a, b);
endmodule

COA/FA_HA.v
module FA_HA (
    input a,
    input b,
    input ci,
    output s,
    output co
);
    wire s1, c1, c2;

    HA ha1 (
        .a(a),
        .b(b),
        .s(s1),
        .c(c1)
    );

    HA ha2 (
        .a(s1),
        .b(ci),
        .s(s),
        .c(c2)
    );

    assign co = c1 | c2;
endmodule

COA/FA_HA_tb.v
`timescale 1ns/1ps

module FA_HA_tb;
    reg a, b, ci;
    wire s, co;

    FA_HA uut (
        .a(a),
        .b(b),
        .ci(ci),
        .s(s),
        .co(co)
    );

    initial begin
        $dumpfile("fa_ha_wave.vcd");
        $dumpvars(0, FA_HA_tb);

        $monitor("t=%0t a=%b b=%b ci=%b -> s=%b co=%b",
                 $time, a, b, ci, s, co);

        // a=0; b=0; ci=0; #10;
        // a=0; b=0; ci=1; #10;
        // a=0; b=1; ci=0; #10;
        // a=0; b=1; ci=1; #10;
        // a=1; b=0; ci=0; #10;
        // a=1; b=0; ci=1; #10;
        // a=1; b=1; ci=0; #10;
        // a=1; b=1; ci=1; #10;
        for(integer i = 1; i < 8; i++)
        begin
            {a, b, ci} = i;
            #10;
            end

        $finish;
    end
endmodule

COA/fa_ha_wave.vcd
$date
	Sun Sep 14 18:47:50 2025
$end
$version
	Icarus Verilog
$end
$timescale
	1ps
$end
$scope module FA_HA_tb $end
$var wire 1 ! s $end
$var wire 1 " co $end
$var reg 1 # a $end
$var reg 1 $ b $end
$var reg 1 % ci $end
$scope module uut $end
$var wire 1 # a $end
$var wire 1 $ b $end
$var wire 1 % ci $end
$var wire 1 " co $end
$var wire 1 & s1 $end
$var wire 1 ! s $end
$var wire 1 ' c2 $end
$var wire 1 ( c1 $end
$scope module ha1 $end
$var wire 1 # a $end
$var wire 1 $ b $end
$var wire 1 ( c $end
$var wire 1 & s $end
$upscope $end
$scope module ha2 $end
$var wire 1 & a $end
$var wire 1 % b $end
$var wire 1 ' c $end
$var wire 1 ! s $end
$upscope $end
$upscope $end
$scope begin $ivl_for_loop0 $end
$var integer 32 ) i [31:0] $end
$upscope $end
$upscope $end
$enddefinitions $end
#0
$dumpvars
b1 )
0(
0'
0&
1%
0$
0#
0"
1!
$end
#10000
1&
1!
1$
0%
b10 )
#20000
1"
0!
1'
1%
b11 )
#30000
0"
1!
0'
1#
0$
0%
b100 )
#40000
1"
0!
1'
1%
b101 )
#50000
0&
1(
0!
0'
1$
0%
b110 )
#60000
1!
1%
b111 )
#70000
b1000 )
