COA/FA/FA.v
module FA (
    input a,       
    input b,       
    input ci,      
    output s,      
    output co      
);
    assign s  = a ^ b ^ ci;                  
    assign co = (a & b) | (a & ci) | (b & ci); 
endmodule

COA/FA_tb.v
`timescale 1ns/1ps

module FA_tb;
    reg a, b, ci;       // inputs
    wire s, co;         // outputs

    // Instantiate the FA module
    FA uut (
        .a(a),
        .b(b),
        .ci(ci),
        .s(s),
        .co(co)
    );

    initial begin
        // Dump waveform data
        $dumpfile("fa_wave.vcd");
        $dumpvars(0, FA_tb);
        
        // Monitor changes
        $monitor("t=%0t a=%b b=%b ci=%b -> s=%b co=%b", 
                $time, a, b, ci, s, co);
        
        // Test all 8 possible input combinations
        a=0; b=0; ci=0; #10;
        a=0; b=0; ci=1; #10;
        a=0; b=1; ci=0; #10;
        a=0; b=1; ci=1; #10;
        a=1; b=0; ci=0; #10;
        a=1; b=0; ci=1; #10;
        a=1; b=1; ci=0; #10;
        a=1; b=1; ci=1; #10;
        
        $finish;
    end
endmodule

COA/fa_wave.vcd
$date
	Mon Aug 11 11:33:09 2025
$end
$version
	Icarus Verilog
$end
$timescale
	1ps
$end
$scope module FA_tb $end
$var wire 1 ! s $end
$var wire 1 " co $end
$var reg 1 # a $end
$var reg 1 $ b $end
$var reg 1 % ci $end
$scope module uut $end
$var wire 1 # a $end
$var wire 1 $ b $end
$var wire 1 % ci $end
$var wire 1 " co $end
$var wire 1 ! s $end
$upscope $end
$upscope $end
$enddefinitions $end
#0
$dumpvars
0%
0$
0#
0"
0!
$end
#10000
1!
1%
#20000
0%
1$
#30000
1"
0!
1%
#40000
0"
1!
0%
0$
1#
#50000
1"
0!
1%
#60000
0%
1$
#70000
1!
1%
