COA/T_FF.v
module T_FF ( 
    input wire clk,
    input wire rst,
    input wire T,
    output reg Q
);
    always @(posedge clk or posedge rst) begin
        if(rst)
        Q <= 0;
        else if(T)
        Q <= ~Q;
    end
    
endmodule

COA/TFF/T_FF_tb.v
`timescale 1ns/1ps

module T_FF_tb;
    reg clk, rst, T;
    wire Q;

    T_FF uut (.clk(clk), .rst(rst), .T(T), .Q(Q));

    always #5 clk = ~clk;

    initial begin
        $dumpfile("T_FF.vcd");
        $dumpvars(0, T_FF_tb);
        $monitor("t=%0t clk=%b rst=%b T=%b -> Q=%b", $time, clk, rst, T, Q);

        //Initialization
        clk = 0;
        rst = 1;
        T = 0;
        #10;
        rst =0;
    
        //Toggle behav
        T = 1;
        #40;
        T = 0;
        #20;
        T = 1;
        #30;

        $finish;
    end    
endmodule

COA/T_FF.vcd
$date
	Mon Sep 15 10:27:05 2025
$end
$version
	Icarus Verilog
$end
$timescale
	1ps
$end
$scope module T_FF_tb $end
$var wire 1 ! Q $end
$var reg 1 " T $end
$var reg 1 # clk $end
$var reg 1 $ rst $end
$scope module uut $end
$var wire 1 " T $end
$var wire 1 # clk $end
$var wire 1 $ rst $end
$var reg 1 ! Q $end
$upscope $end
$upscope $end
$enddefinitions $end
#0
$dumpvars
1$
0#
0"
0!
$end
#5000
1#
#10000
0#
1"
0$
#15000
1!
1#
#20000
0#
#25000
0!
1#
#30000
0#
#35000
1!
1#
#40000
0#
#45000
0!
1#
#50000
0#
0"
#55000
1#
#60000
0#
#65000
1#
#70000
0#
1"
#75000
1!
1#
#80000
0#
#85000
0!
1#
#90000
0#
#95000
1!
1#
