COA/post minor/Direct Mapping/x.v
module DirectMap(
    input  [10:0] addr,
    input  [7:0]  din,
    input         clk,
    input         we,
    output reg [7:0] dout,
    output reg       hit
);
    reg  [3:0] tag  [0:15];
    reg  [7:0] data [0:15];
    reg        valid[0:15];

    wire [3:0] index;
    wire [2:0] t;

    assign index = addr[3:0];
    assign t     = addr[10:7];

    always @(posedge clk) begin
        if (we) begin
            tag[index]   <= t;
            data[index]  <= din;
            valid[index] <= 1;
        end 
        else begin
            if (valid[index] && tag[index] == t) begin
                dout <= data[index];
                hit  <= 1;
            end 
            else begin
                dout <= 8'b0;
                hit  <= 0;
            end
        end
    end
endmodule

COA/Direct Mapping/x_tb.v
`timescale 1ns/1ps

module DirectMap_tb;
    reg        clk;
    reg        rst;
    reg        read;
    reg        we;
    reg  [10:0] addr;
    reg  [7:0]  din;
    wire [7:0]  dout;
    wire        hit;

    DirectMap dut (
        .addr(addr),
        .din(din),
        .clk(clk),
        .we(we),
        .dout(dout),
        .hit(hit)
    );

    initial begin
        clk = 0;
        forever #5 clk = ~clk;
    end

    function [10:0] make_addr;
        input [3:0] tag;
        input [3:0] index;
        begin
            make_addr = (tag << 7) | index;
        end
    endfunction

    task show;
        input [10:0] a;
        input [7:0] w;
        input r;
        input wr;
        begin
            #1;
            $display("%0t | addr=%0d tag=%b idx=%b | we=%b read=%b | hit=%b dout=%02h written=%02h",
                     $time, a, a[10:7], a[6:0], wr, r, hit, dout, w);
        end
    endtask

    initial begin
        $dumpfile("DirectMap.vcd");
        $dumpvars(0, DirectMap_tb);

        $display("\nDirectMap testbench");
        $display("Registers: 16 lines, tag=4 bits, index=7 bits(used partly), data=8 bits");
        $display("Time | addr tag idx | we read | hit dout written");
        $display("------------------------------------------------");

        rst = 1; read = 0; we = 0; addr = 0; din = 0;
        #12;
        rst = 0;
        #8;

       we = 1; read = 0;
        addr = make_addr(4'b0001, 4'd0); din = 8'hA1; show(addr,din,read,we); #10;
        addr = make_addr(4'b0010, 4'd1); din = 8'hB2; show(addr,din,read,we); #10;
        addr = make_addr(4'b0011, 4'd2); din = 8'hC3; show(addr,din,read,we); #10;
        addr = make_addr(4'b0100, 4'd3); din = 8'hD4; show(addr,din,read,we); #10;
        we = 0;

        read = 1; din = 8'h00;

        addr = make_addr(4'b0001, 4'd0); show(addr,din,read,we); #10;
        addr = make_addr(4'b0010, 4'd1); show(addr,din,read,we); #10;

        addr = make_addr(4'b1111, 4'd4); show(addr,din,read,we); #10;

        we = 1; read = 0;
        addr = make_addr(4'b1001, 4'd0); din = 8'h9A; show(addr,din,read,we); #10;
        we = 0; read = 1;
        addr = make_addr(4'b0001, 4'd0); show(addr,din,read,we); #10;

        addr = make_addr(4'b1001, 4'd0); show(addr,din,read,we); #10;

        $finish;
    end

endmodule

COA/post minor/Direct Mapping/DirectMap.vcd
$date
	Mon Nov 03 23:55:37 2025
$end
$version
	Icarus Verilog
$end
$timescale
	1ps
$end
$scope module DirectMap_tb $end
$var wire 1 ! hit $end
$var wire 8 " dout [7:0] $end
$var reg 11 # addr [10:0] $end
$var reg 1 $ clk $end
$var reg 8 % din [7:0] $end
$var reg 1 & read $end
$var reg 1 ' rst $end
$var reg 1 ( we $end
$scope function make_addr $end
$var reg 4 ) index [3:0] $end
$var reg 4 * tag [3:0] $end
$upscope $end
$scope module dut $end
$var wire 11 + addr [10:0] $end
$var wire 1 $ clk $end
$var wire 8 , din [7:0] $end
$var wire 1 ( we $end
$var wire 3 - t [2:0] $end
$var wire 4 . index [3:0] $end
$var reg 8 / dout [7:0] $end
$var reg 1 ! hit $end
$upscope $end
$scope task show $end
$var reg 11 0 a [10:0] $end
$var reg 1 1 r $end
$var reg 8 2 w [7:0] $end
$var reg 1 3 wr $end
$upscope $end
$upscope $end
$enddefinitions $end
#0
$dumpvars
x3
bx 2
x1
bx 0
bx /
b0 .
b0 -
b0 ,
b0 +
bx *
bx )
0(
1'
0&
b0 %
0$
b0 #
bx "
x!
$end
#5000
0!
b0 "
b0 /
1$
#10000
0$
#12000
0'
#15000
1$
#20000
b1 -
0$
13
01
b10100001 2
b10000000 0
b10100001 %
b10100001 ,
b10000000 #
b10000000 +
b1 *
b0 )
1(
#25000
1$
#30000
0$
#31000
b10 -
b1 .
b10110010 2
b100000001 0
b10110010 %
b10110010 ,
b100000001 #
b100000001 +
b10 *
b1 )
#35000
1$
#40000
0$
#42000
b11 -
b10 .
b11000011 2
b110000010 0
b11000011 %
b11000011 ,
b110000010 #
b110000010 +
b11 *
b10 )
#45000
1$
#50000
0$
#53000
b100 -
b11 .
b11010100 2
b1000000011 0
b11010100 %
b11010100 ,
b1000000011 #
b1000000011 +
b100 *
b11 )
#55000
1$
#60000
0$
#64000
b1 -
b0 .
03
11
b0 2
b10000000 0
b10000000 #
b10000000 +
b1 *
b0 )
b0 %
b0 ,
1&
0(
#65000
1!
b10100001 "
b10100001 /
1$
#70000
0$
#75000
0!
b0 "
b0 /
b10 -
b1 .
1$
b100000001 0
b100000001 #
b100000001 +
b10 *
b1 )
#80000
0$
#85000
1!
b10110010 "
b10110010 /
1$
#86000
b111 -
b100 .
b11110000100 0
b11110000100 #
b11110000100 +
b1111 *
b100 )
#90000
0$
#95000
0!
b0 "
b0 /
1$
#97000
b1 -
b0 .
13
01
b10011010 2
b10010000000 0
b10011010 %
b10011010 ,
b10010000000 #
b10010000000 +
b1001 *
b0 )
0&
1(
#100000
0$
#105000
1$
#108000
03
11
b10000000 0
b10000000 #
b10000000 +
b1 *
1&
0(
#110000
0$
#115000
1!
b10011010 "
b10011010 /
1$
#119000
b10010000000 0
b10010000000 #
b10010000000 +
b1001 *
