COA/4x3RAM/RAM4x3.v
module RAM4x3 (
    input [1:0] Addr,
    input [2:0] DataIn,
    input Write,
    input Clk,
    output reg [2:0] DataOut
);
    reg [2:0] mem [3:0];

    always @(posedge Clk) begin
        if (Write)
            mem[Addr] <= DataIn;
    end

    always @(*) begin
        if (!Write)
            DataOut = mem[Addr];
        else
            DataOut = 3'bzzz;
    end
endmodule

COA/4x3RAM/RAM4x3_tb.v
`timescale 1ns/1ps

module RAM4x3_tb;
    reg [1:0] Addr;
    reg [2:0] DataIn;
    reg Write, Clk;
    wire [2:0] DataOut;

    RAM4x3 uut (.Addr(Addr), .DataIn(DataIn), .Write(Write), .Clk(Clk), .DataOut(DataOut));

    initial begin
        Clk = 0;
        forever #5 Clk = ~Clk;
    end

    initial begin
        $dumpfile("RAM4x3.vcd");
        $dumpvars(0, RAM4x3_tb);

        $display("Time\tClk\tWrite\tAddr\tDataIn\tDataOut");
        $monitor("%0t\t%b\t%b\t%02b\t%03b\t%03b", $time, Clk, Write, Addr, DataIn, DataOut);

        Write = 1;
        Addr = 2'b00; DataIn = 3'b101; #10;
        Addr = 2'b01; DataIn = 3'b010; #10;
        Addr = 2'b10; DataIn = 3'b111; #10;
        Addr = 2'b11; DataIn = 3'b000; #10;

        Write = 0;
        Addr = 2'b00; #10;
        Addr = 2'b01; #10;
        Addr = 2'b10; #10;
        Addr = 2'b11; #10;

        $finish;
    end
endmodule

COA/post minor/4x3RAM/RAM4x3.vcd
$date
	Mon Oct 13 23:34:46 2025
$end
$version
	Icarus Verilog
$end
$timescale
	1ps
$end
$scope module RAM4x3_tb $end
$var wire 3 ! DataOut [2:0] $end
$var reg 2 " Addr [1:0] $end
$var reg 1 # Clk $end
$var reg 3 $ DataIn [2:0] $end
$var reg 1 % Write $end
$scope module uut $end
$var wire 2 & Addr [1:0] $end
$var wire 1 # Clk $end
$var wire 3 ' DataIn [2:0] $end
$var wire 1 % Write $end
$var reg 3 ( DataOut [2:0] $end
$upscope $end
$upscope $end
$enddefinitions $end
#0
$dumpvars
bz (
b101 '
b0 &
1%
b101 $
0#
b0 "
bz !
$end
#5000
1#
#10000
0#
b10 $
b10 '
b1 "
b1 &
#15000
1#
#20000
0#
b111 $
b111 '
b10 "
b10 &
#25000
1#
#30000
0#
b0 $
b0 '
b11 "
b11 &
#35000
1#
#40000
b101 !
b101 (
0#
b0 "
b0 &
0%
#45000
1#
#50000
b10 !
b10 (
0#
b1 "
b1 &
#55000
1#
#60000
b111 !
b111 (
0#
b10 "
b10 &
#65000
1#
#70000
b0 !
b0 (
0#
b11 "
b11 &
