COA/post minor/MemoryCell/memCell.v
module memory_cell(
    input D, Read, Write, Clk, Rst,
    output reg Q,
    output Out
);
    always @(posedge Clk or posedge Rst) begin
        if (Rst)
            Q <= 0;
        else if (Write)
            Q <= D;
    end

    assign Out = (Read) ? Q : 1'bz;
endmodule

COA/post minor/MemoryCell/memCell_tb.v
`timescale 1ns/1ps
module memory_cell_tb;
    reg D, Read, Write, Clk;
    wire Out;
    wire Q;

    memory_cell uut (.D(D), .Read(Read), .Write(Write), .Clk(Clk), .Q(Q), .Out(Out));

    initial Clk = 0;
    always #5 Clk = ~Clk;
    initial begin
        $dumpfile("memory_cell.vcd");
        $dumpvars(0, memory_cell_tb);
        $monitor("t=%0t | D=%b Read=%b Write=%b Q=%b Out=%b", $time, D, Read, Write, Q, Out);

        // Initialize
        D=0; Read=0; Write=0; #10;

        D=1; Write=1; #10;
        Write=0; #10;

        Read=1; #10;
        Read=0; #10;

        D=0; Write=1; #10;
        Write=0; #10;

        Read=1; #10;
        Read=0; #10;

        $finish;
    end
endmodule

COA/MemoryCell/memory_cell.vcd
$date
	Mon Oct 06 00:21:40 2025
$end
$version
	Icarus Verilog
$end
$timescale
	1ps
$end
$scope module memory_cell_tb $end
$var wire 1 ! Q $end
$var wire 1 " Out $end
$var reg 1 # Clk $end
$var reg 1 $ D $end
$var reg 1 % Read $end
$var reg 1 & Write $end
$scope module uut $end
$var wire 1 # Clk $end
$var wire 1 $ D $end
$var wire 1 % Read $end
$var wire 1 ' Rst $end
$var wire 1 & Write $end
$var wire 1 " Out $end
$var reg 1 ! Q $end
$upscope $end
$upscope $end
$enddefinitions $end
#0
$dumpvars
z'
0&
0%
0$
0#
z"
x!
$end
#5000
1#
#10000
0#
1&
1$
#15000
1!
1#
#20000
0#
0&
#25000
1#
#30000
1"
0#
1%
#35000
1#
#40000
z"
0#
0%
#45000
1#
#50000
0#
1&
0$
#55000
0!
1#
#60000
0#
0&
#65000
1#
#70000
0"
0#
1%
#75000
1#
#80000
z"
0#
0%
