coa_minor/que1.v
module que1 (
    input [4:1] B,
    output [4:1] X
);

    wire [7:1] w;

    assign w[7] = B[3] & B[2];
    assign w[6] = B[3] & B[1];
    assign w[5] = B[3] & ~B[2] & ~B[1];
    assign w[4] = B[3] & B[1];
    assign w[3] = ~B[3] & B[2];
    assign w[2] = ~B[2] & ~B[1];
    assign w[1] = B[2] & B[1];

    assign X[4] = B[4] | w[7] | w[6];
    assign X[3] = w[5] | w[4] | w[3];
    assign X[2] = w[2] | w[1];
    assign X[1] = ~B[1];
    
endmodule

coa_minor/que1_tb.v
`timescale 1ns/1ps  
module que1_tb;
    reg [4:1] B;
    wire [4:1] X;

    que1 uut(.B(B), .X(X));

    initial begin
        $dumpfile("que1.vcd");
        $dumpvars(0, que1_tb);
        $monitor("t = %0t B = %b -> X = %b", $time, B, X);

        for (integer i = 0; i <= 8; i++) begin
            B = i;
            #10;
        end
        $finish;
    end
endmodule

coa_minor/que1.vcd
$date
	Mon Sep 15 12:02:24 2025
$end
$version
	Icarus Verilog
$end
$timescale
	1ps
$end
$scope module que1_tb $end
$var wire 4 ! X [4:1] $end
$var reg 4 " B [4:1] $end
$scope module uut $end
$var wire 4 # B [4:1] $end
$var wire 7 $ w [7:1] $end
$var wire 4 % X [4:1] $end
$upscope $end
$scope begin $ivl_for_loop0 $end
$var integer 32 & i [31:0] $end
$upscope $end
$upscope $end
$enddefinitions $end
#0
$dumpvars
b0 &
b11 %
b10 $
b0 #
b0 "
b11 !
$end
#10000
b0 $
b0 !
b0 %
b1 "
b1 #
b1 &
#20000
b100 $
b101 !
b101 %
b10 "
b10 #
b10 &
#30000
b101 $
b110 !
b110 %
b11 "
b11 #
b11 &
#40000
b10010 $
b111 !
b111 %
b100 "
b100 #
b100 &
#50000
b101000 $
b1100 !
b1100 %
b101 "
b101 #
b101 &
#60000
b1000000 $
b1001 !
b1001 %
b110 "
b110 #
b110 &
#70000
b1101001 $
b1110 !
b1110 %
b111 "
b111 #
b111 &
#80000
b10 $
b1011 !
b1011 %
b1000 "
b1000 #
b1000 &
#90000
b1001 &
