coa_minor/que2.v
module x(
    input clk,
    input reset,
    output q1, q2, q3
);

    reg q1, q2, q3_reg;

    always @(posedge clk or posedge reset) begin
        if (reset) begin
            q1 <= 0;
            q2 <= 0;
            q3_reg <= 0;
        end else begin
            q1 <= ~q1;

            if (q1)
                q2 <= ~q2;

            if (q1 & q2)
                q3_reg <= ~q3_reg;
        end
    end

    assign q3 = q3_reg;

endmodule

coa_minor/que2_tb.v
`timescale 1ns/1ps
module x_tb;
    reg clk, reset;
    wire q1, q2, q3;

    x uut(.clk(clk), .reset(reset), .q1(q1), .q2(q2), .q3(q3));

    initial clk = 0;
    always #10 clk = ~clk;

    initial begin
        $dumpfile("x.vcd");
        $dumpvars(0, x_tb);
        $monitor("t=%0t clk=%b reset=%b q1 = %b q2=%b q3 = %b ", $time, clk, reset, q1, q2, q3);

        reset = 1; #10; reset = 0;
        #200;
        $finish;
    end
endmodule

coa_minor/x.vcd
$date
	Mon Sep 15 12:30:39 2025
$end
$version
	Icarus Verilog
$end
$timescale
	1ps
$end
$scope module x_tb $end
$var wire 1 ! q3 $end
$var wire 1 " q2 $end
$var wire 1 # q1 $end
$var reg 1 $ clk $end
$var reg 1 % reset $end
$scope module uut $end
$var wire 1 $ clk $end
$var wire 1 ! q3 $end
$var wire 1 % reset $end
$var reg 1 # q1 $end
$var reg 1 " q2 $end
$var reg 1 & q3_reg $end
$upscope $end
$upscope $end
$enddefinitions $end
#0
$dumpvars
0&
1%
0$
0#
0"
0!
$end
#10000
1#
0%
1$
#20000
0$
#30000
1"
0#
1$
#40000
0$
#50000
1#
1$
#60000
0$
#70000
1!
1&
0"
0#
1$
#80000
0$
#90000
1#
1$
#100000
0$
#110000
1"
0#
1$
#120000
0$
#130000
1#
1$
#140000
0$
#150000
0!
0&
0"
0#
1$
#160000
0$
#170000
1#
1$
#180000
0$
#190000
1"
0#
1$
#200000
0$
#210000
1#
1$
